e2L.py
e2L-0.2.1.dist-info/METADATA
e2L-0.2.1.dist-info/WHEEL
e2L-0.2.1.dist-info/top_level.txt
e2L-0.2.1.dist-info/RECORD
