Metadata-Version: 2.2
Name: e2L
Version: 0.2.1
Summary: Generate custom PDF checklists with eBird occurrence data.
Home-page: https://github.com/Zoziologie/ebird2latex
Download-URL: https://github.com/Zoziologie/ebird2latex/archive/refs/tags/v0.0.3.tar.gz
Author: Raphaël Nussbaumer
Author-email: rafnuss@gmail.com
License: MIT
Keywords: python,eBird,LaTeX
Classifier: Programming Language :: Python :: 3
Classifier: Programming Language :: Python :: 3.8
Classifier: License :: OSI Approved :: MIT License
Classifier: Operating System :: OS Independent
Classifier: Intended Audience :: Developers
Classifier: Intended Audience :: Science/Research
Requires-Dist: requests
Requires-Dist: lxml
Dynamic: author
Dynamic: author-email
Dynamic: classifier
Dynamic: description
Dynamic: description-content-type
Dynamic: download-url
Dynamic: home-page
Dynamic: keywords
Dynamic: license
Dynamic: requires-dist
Dynamic: summary
